pyhacks
