Metadata-Version: 2.1
Name: pyhacks
Version: 1.0.18
Summary: Ease developers to use queue/threads functions to handle big amount of data
Home-page: https://github.com/Quitten/pyhacks
Author: Barak Tawily
Author-email: barak.tawily@gmail.com
License: MIT
Download-URL: https://github.com/Quitten/pyhacks/releases/v_01.tar.gz
Keywords: threads,queue
Platform: UNKNOWN
Classifier: Development Status :: 4 - Beta
Classifier: Intended Audience :: Developers
Classifier: Topic :: Software Development :: Build Tools
Classifier: License :: OSI Approved :: MIT License
Classifier: Programming Language :: Python :: 3
Classifier: Programming Language :: Python :: 3.4
Classifier: Programming Language :: Python :: 3.5
Classifier: Programming Language :: Python :: 3.6
Classifier: Programming Language :: Python :: 3.7
